torchopt/__init__.py
torchopt/api.py
torchopt/utils.py
torchopt/model/__init__.py
torchopt/model/resnet.py
torchopt/model/resnet56_cifar10_0.9320_45k.pth
torchopt/model/vgg16_cifar10_0.9225_45k.pth
torchopt/optim/__init__.py
torchopt/optim/cache.py
torchopt/optim/constraint.py
torchopt/optim/objective.py
torchopt/optim/optimizer.py
torchopt/optim/utils.py
torchopt/prune/__init__.py
torchopt/prune/prune.py
torchopt/prune/pruner.py
torchopt/prune/scoring.py
torchopt/train/__init__.py
torchopt/train/distillation.py
torchopt/train/loader.py
torch_optim-0.0.4.dist-info/LICENSE
torch_optim-0.0.4.dist-info/METADATA
torch_optim-0.0.4.dist-info/WHEEL
torch_optim-0.0.4.dist-info/top_level.txt
torch_optim-0.0.4.dist-info/RECORD
