Metadata-Version: 2.1
Name: torch-optim
Version: 0.0.4
Summary: PyTorch models optimization by neural network pruning
Home-page: https://github.com/r-papso/torch-optimizer
Author: Rastislav Papso
Author-email: rastislav.papso@gmail.com
License: UNKNOWN
Project-URL: Bug Tracker, https://github.com/r-papso/torch-optimizer/issues
Platform: UNKNOWN
Classifier: Programming Language :: Python :: 3
Classifier: License :: OSI Approved :: MIT License
Classifier: Operating System :: OS Independent
Requires-Python: >=3.7
License-File: LICENSE
